{
  "name": "Beginner Condition Weaver [SC]",
  "description": "Build and rotation created by Snow Crows.\n\nPublished Dec 2, 2022\nUpdated Dec 30, 2022\nNovember 2022 Balance",
  "logUrl": "https://dps.report/m2fR-20221230-135117_golem",
  "buildChatCode": "[&DQYfFRomOBV0AAAAcwAAAMsAAAA1FwAAEhcAAAAAAAAAAAAAAAAAAAAAAAA=]",
  "buildUrl": "https://snowcrows.com/en/builds/elementalist/weaver/beginner-condition-weaver",
  "decodedBuildTemplate": {
    "profession": 6,
    "specializations": [
      {
        "id": 31,
        "traits": [
          1,
          1,
          1
        ]
      },
      {
        "id": 26,
        "traits": [
          2,
          1,
          2
        ]
      },
      {
        "id": 56,
        "traits": [
          1,
          1,
          1
        ]
      }
    ],
    "skills": {
      "terrestrial": {
        "heal": 116,
        "utilities": [
          115,
          203,
          5941
        ],
        "elite": 5906
      },
      "aquatic": {
        "heal": 0,
        "utilities": [
          0,
          0,
          0
        ],
        "elite": 0
      }
    },
    "specific": [
      0,
      0,
      0,
      0,
      0,
      0,
      0,
      0,
      0,
      0,
      0,
      0,
      0,
      0,
      0,
      0
    ]
  },
  "notes": [
    {
      "time": 0,
      "duration": 512,
      "noteType": "Utility2",
      "abilityId": 5542
    },
    {
      "time": 432,
      "duration": 0,
      "noteType": "Profession1",
      "abilityId": -7
    },
    {
      "time": 512,
      "duration": 448,
      "noteType": "Weapon1",
      "abilityId": 5508
    },
    {
      "time": 560,
      "duration": 0,
      "noteType": "Profession1",
      "abilityId": 43470
    },
    {
      "time": 960,
      "duration": 480,
      "noteType": "Weapon3",
      "abilityId": 5675
    },
    {
      "time": 1440,
      "duration": 368,
      "noteType": "Weapon5",
      "abilityId": 51711
    },
    {
      "time": 1808,
      "duration": 544,
      "noteType": "Weapon4",
      "abilityId": 5497
    },
    {
      "time": 2352,
      "duration": 608,
      "noteType": "Weapon1",
      "abilityId": 5508
    },
    {
      "time": 2960,
      "duration": 592,
      "noteType": "Weapon1",
      "abilityId": 5508
    },
    {
      "time": 3552,
      "duration": 448,
      "noteType": "Weapon1",
      "abilityId": 5508
    },
    {
      "time": 4000,
      "duration": 672,
      "noteType": "Weapon2",
      "abilityId": 5692
    },
    {
      "time": 4160,
      "duration": 0,
      "noteType": "Profession4",
      "abilityId": -14
    },
    {
      "time": 4672,
      "duration": 496,
      "noteType": "Weapon1",
      "abilityId": 5500
    },
    {
      "time": 5168,
      "duration": 912,
      "noteType": "Weapon3",
      "abilityId": 42954
    },
    {
      "time": 5520,
      "duration": 0,
      "noteType": "Utility3",
      "abilityId": 40183
    },
    {
      "time": 6080,
      "duration": 1408,
      "noteType": "Weapon1",
      "abilityId": 5500
    },
    {
      "time": 7488,
      "duration": 1104,
      "noteType": "Weapon1",
      "abilityId": 5500
    },
    {
      "time": 7680,
      "duration": 0,
      "noteType": "Profession1",
      "abilityId": -7
    },
    {
      "time": 8592,
      "duration": 688,
      "noteType": "Weapon2",
      "abilityId": 5692
    },
    {
      "time": 9280,
      "duration": 592,
      "noteType": "Weapon1",
      "abilityId": 5508
    },
    {
      "time": 9872,
      "duration": 368,
      "noteType": "Weapon1",
      "abilityId": 5508
    },
    {
      "time": 10240,
      "duration": 512,
      "noteType": "Utility2",
      "abilityId": 5542
    },
    {
      "time": 10752,
      "duration": 400,
      "noteType": "Weapon1",
      "abilityId": 5508
    },
    {
      "time": 10992,
      "duration": 0,
      "noteType": "Profession1",
      "abilityId": 43470
    },
    {
      "time": 11152,
      "duration": 480,
      "noteType": "Weapon3",
      "abilityId": 5675
    },
    {
      "time": 11632,
      "duration": 384,
      "noteType": "Weapon5",
      "abilityId": 51711
    },
    {
      "time": 12016,
      "duration": 576,
      "noteType": "Weapon1",
      "abilityId": 5508
    },
    {
      "time": 12592,
      "duration": 608,
      "noteType": "Weapon1",
      "abilityId": 5508
    },
    {
      "time": 13200,
      "duration": 592,
      "noteType": "Weapon1",
      "abilityId": 5508
    },
    {
      "time": 13792,
      "duration": 448,
      "noteType": "Weapon1",
      "abilityId": 5508
    },
    {
      "time": 14240,
      "duration": 672,
      "noteType": "Weapon2",
      "abilityId": 5692
    },
    {
      "time": 14480,
      "duration": 0,
      "noteType": "Profession4",
      "abilityId": -14
    },
    {
      "time": 14912,
      "duration": 768,
      "noteType": "Weapon2",
      "abilityId": 5695
    },
    {
      "time": 15671,
      "duration": 0,
      "noteType": "Weapon2",
      "abilityId": 5780
    },
    {
      "time": 15680,
      "duration": 560,
      "noteType": "Weapon4",
      "abilityId": 5497
    },
    {
      "time": 16240,
      "duration": 80,
      "noteType": "Weapon1",
      "abilityId": 5500
    },
    {
      "time": 16320,
      "duration": 912,
      "noteType": "Weapon3",
      "abilityId": 42954
    },
    {
      "time": 17232,
      "duration": 1408,
      "noteType": "Weapon1",
      "abilityId": 5500
    },
    {
      "time": 17392,
      "duration": 0,
      "noteType": "Utility3",
      "abilityId": 40183
    },
    {
      "time": 17872,
      "duration": 0,
      "noteType": "Profession1",
      "abilityId": -7
    },
    {
      "time": 18640,
      "duration": 272,
      "noteType": "Weapon1",
      "abilityId": 5508
    },
    {
      "time": 18912,
      "duration": 688,
      "noteType": "Weapon2",
      "abilityId": 5692
    },
    {
      "time": 19600,
      "duration": 592,
      "noteType": "Weapon1",
      "abilityId": 5508
    },
    {
      "time": 20192,
      "duration": 320,
      "noteType": "Weapon1",
      "abilityId": 5508
    },
    {
      "time": 20512,
      "duration": 528,
      "noteType": "Utility2",
      "abilityId": 5542
    },
    {
      "time": 21040,
      "duration": 592,
      "noteType": "Weapon1",
      "abilityId": 5508
    },
    {
      "time": 21200,
      "duration": 0,
      "noteType": "Profession1",
      "abilityId": 43470
    },
    {
      "time": 21632,
      "duration": 480,
      "noteType": "Weapon3",
      "abilityId": 5675
    },
    {
      "time": 22112,
      "duration": 368,
      "noteType": "Weapon5",
      "abilityId": 51711
    },
    {
      "time": 22480,
      "duration": 592,
      "noteType": "Weapon1",
      "abilityId": 5508
    },
    {
      "time": 23072,
      "duration": 608,
      "noteType": "Weapon1",
      "abilityId": 5508
    },
    {
      "time": 23680,
      "duration": 592,
      "noteType": "Weapon1",
      "abilityId": 5508
    },
    {
      "time": 24272,
      "duration": 240,
      "noteType": "Weapon1",
      "abilityId": 5508
    },
    {
      "time": 24512,
      "duration": 688,
      "noteType": "Weapon2",
      "abilityId": 5692
    },
    {
      "time": 24752,
      "duration": 0,
      "noteType": "Profession4",
      "abilityId": -14
    },
    {
      "time": 25200,
      "duration": 112,
      "noteType": "Weapon1",
      "abilityId": 5500
    },
    {
      "time": 25312,
      "duration": 1280,
      "noteType": "Weapon2",
      "abilityId": 5695
    },
    {
      "time": 26071,
      "duration": 0,
      "noteType": "Weapon2",
      "abilityId": 5780
    },
    {
      "time": 26592,
      "duration": 768,
      "noteType": "Weapon1",
      "abilityId": 5500
    },
    {
      "time": 27360,
      "duration": 912,
      "noteType": "Weapon3",
      "abilityId": 42954
    },
    {
      "time": 28160,
      "duration": 0,
      "noteType": "Profession1",
      "abilityId": -7
    },
    {
      "time": 28272,
      "duration": 608,
      "noteType": "Weapon1",
      "abilityId": 5508
    },
    {
      "time": 28880,
      "duration": 400,
      "noteType": "Weapon1",
      "abilityId": 5508
    },
    {
      "time": 29280,
      "duration": 672,
      "noteType": "Weapon2",
      "abilityId": 5692
    },
    {
      "time": 29952,
      "duration": 608,
      "noteType": "Weapon1",
      "abilityId": 5508
    },
    {
      "time": 30560,
      "duration": 192,
      "noteType": "Weapon1",
      "abilityId": 5508
    },
    {
      "time": 30752,
      "duration": 528,
      "noteType": "Utility2",
      "abilityId": 5542
    },
    {
      "time": 31280,
      "duration": 592,
      "noteType": "Weapon1",
      "abilityId": 5508
    },
    {
      "time": 31760,
      "duration": 0,
      "noteType": "Profession1",
      "abilityId": 43470
    },
    {
      "time": 31872,
      "duration": 208,
      "noteType": "Weapon1",
      "abilityId": 5508
    },
    {
      "time": 32080,
      "duration": 480,
      "noteType": "Weapon3",
      "abilityId": 5675
    },
    {
      "time": 32560,
      "duration": 288,
      "noteType": "Weapon1",
      "abilityId": 5508
    },
    {
      "time": 32847,
      "duration": 352,
      "noteType": "Weapon5",
      "abilityId": 51711
    },
    {
      "time": 33200,
      "duration": 560,
      "noteType": "Weapon4",
      "abilityId": 5497
    },
    {
      "time": 33760,
      "duration": 592,
      "noteType": "Weapon1",
      "abilityId": 5508
    },
    {
      "time": 34352,
      "duration": 608,
      "noteType": "Weapon1",
      "abilityId": 5508
    },
    {
      "time": 34960,
      "duration": 32,
      "noteType": "Weapon1",
      "abilityId": 5508
    },
    {
      "time": 34992,
      "duration": 688,
      "noteType": "Weapon2",
      "abilityId": 5692
    },
    {
      "time": 35280,
      "duration": 0,
      "noteType": "Profession4",
      "abilityId": -14
    },
    {
      "time": 35680,
      "duration": 752,
      "noteType": "Weapon2",
      "abilityId": 5695
    },
    {
      "time": 35792,
      "duration": 0,
      "noteType": "Utility3",
      "abilityId": 40183
    },
    {
      "time": 36432,
      "duration": 1408,
      "noteType": "Weapon1",
      "abilityId": 5500
    },
    {
      "time": 36439,
      "duration": 0,
      "noteType": "Weapon2",
      "abilityId": 5780
    },
    {
      "time": 37840,
      "duration": 112,
      "noteType": "Weapon1",
      "abilityId": 5500
    },
    {
      "time": 37952,
      "duration": 928,
      "noteType": "Weapon3",
      "abilityId": 42954
    },
    {
      "time": 38640,
      "duration": 0,
      "noteType": "Profession1",
      "abilityId": -7
    },
    {
      "time": 38880,
      "duration": 592,
      "noteType": "Weapon1",
      "abilityId": 5508
    },
    {
      "time": 39472,
      "duration": 240,
      "noteType": "Weapon1",
      "abilityId": 5508
    },
    {
      "time": 39712,
      "duration": 688,
      "noteType": "Weapon2",
      "abilityId": 5692
    },
    {
      "time": 40400,
      "duration": 592,
      "noteType": "Weapon1",
      "abilityId": 5508
    },
    {
      "time": 40992,
      "duration": 528,
      "noteType": "Utility2",
      "abilityId": 5542
    },
    {
      "time": 41520,
      "duration": 592,
      "noteType": "Weapon1",
      "abilityId": 5508
    },
    {
      "time": 42080,
      "duration": 0,
      "noteType": "Profession1",
      "abilityId": 43470
    },
    {
      "time": 42112,
      "duration": 288,
      "noteType": "Weapon1",
      "abilityId": 5508
    },
    {
      "time": 42400,
      "duration": 480,
      "noteType": "Weapon3",
      "abilityId": 5675
    },
    {
      "time": 42880,
      "duration": 352,
      "noteType": "Weapon5",
      "abilityId": 51711
    },
    {
      "time": 43232,
      "duration": 608,
      "noteType": "Weapon1",
      "abilityId": 5508
    },
    {
      "time": 43840,
      "duration": 592,
      "noteType": "Weapon1",
      "abilityId": 5508
    },
    {
      "time": 44432,
      "duration": 608,
      "noteType": "Weapon1",
      "abilityId": 5508
    },
    {
      "time": 45040,
      "duration": 400,
      "noteType": "Weapon1",
      "abilityId": 5508
    },
    {
      "time": 45440,
      "duration": 672,
      "noteType": "Weapon2",
      "abilityId": 5692
    },
    {
      "time": 45632,
      "duration": 0,
      "noteType": "Profession4",
      "abilityId": -14
    },
    {
      "time": 46032,
      "duration": 0,
      "noteType": "Utility3",
      "abilityId": 40183
    },
    {
      "time": 46112,
      "duration": 768,
      "noteType": "Weapon2",
      "abilityId": 5695
    },
    {
      "time": 46871,
      "duration": 0,
      "noteType": "Weapon2",
      "abilityId": 5780
    },
    {
      "time": 46880,
      "duration": 240,
      "noteType": "Weapon1",
      "abilityId": 5500
    },
    {
      "time": 47120,
      "duration": 560,
      "noteType": "Weapon4",
      "abilityId": 5497
    },
    {
      "time": 47680,
      "duration": 960,
      "noteType": "Weapon1",
      "abilityId": 5500
    },
    {
      "time": 48640,
      "duration": 912,
      "noteType": "Weapon3",
      "abilityId": 42954
    },
    {
      "time": 49472,
      "duration": 0,
      "noteType": "Profession1",
      "abilityId": -7
    },
    {
      "time": 49552,
      "duration": 609,
      "noteType": "Weapon1",
      "abilityId": 5508
    },
    {
      "time": 50161,
      "duration": 79,
      "noteType": "Weapon1",
      "abilityId": 5508
    },
    {
      "time": 50240,
      "duration": 672,
      "noteType": "Weapon2",
      "abilityId": 5692
    },
    {
      "time": 50912,
      "duration": 480,
      "noteType": "Weapon1",
      "abilityId": 5508
    },
    {
      "time": 51392,
      "duration": 528,
      "noteType": "Utility2",
      "abilityId": 5542
    },
    {
      "time": 51920,
      "duration": 592,
      "noteType": "Weapon1",
      "abilityId": 5508
    },
    {
      "time": 52512,
      "duration": 608,
      "noteType": "Weapon1",
      "abilityId": 5508
    },
    {
      "time": 52768,
      "duration": 0,
      "noteType": "Profession1",
      "abilityId": 43470
    },
    {
      "time": 53120,
      "duration": 32,
      "noteType": "Weapon1",
      "abilityId": 5508
    },
    {
      "time": 53152,
      "duration": 480,
      "noteType": "Weapon3",
      "abilityId": 5675
    },
    {
      "time": 53632,
      "duration": 368,
      "noteType": "Weapon5",
      "abilityId": 51711
    },
    {
      "time": 54000,
      "duration": 592,
      "noteType": "Weapon1",
      "abilityId": 5508
    },
    {
      "time": 54592,
      "duration": 608,
      "noteType": "Weapon1",
      "abilityId": 5508
    },
    {
      "time": 55200,
      "duration": 592,
      "noteType": "Weapon1",
      "abilityId": 5508
    },
    {
      "time": 55792,
      "duration": 320,
      "noteType": "Weapon1",
      "abilityId": 5508
    },
    {
      "time": 56112,
      "duration": 688,
      "noteType": "Weapon2",
      "abilityId": 5692
    },
    {
      "time": 56272,
      "duration": 0,
      "noteType": "Profession4",
      "abilityId": -14
    },
    {
      "time": 56800,
      "duration": 752,
      "noteType": "Weapon2",
      "abilityId": 5695
    },
    {
      "time": 57552,
      "duration": 1408,
      "noteType": "Weapon1",
      "abilityId": 5500
    },
    {
      "time": 57559,
      "duration": 0,
      "noteType": "Weapon2",
      "abilityId": 5780
    },
    {
      "time": 58352,
      "duration": 0,
      "noteType": "Utility3",
      "abilityId": 40183
    },
    {
      "time": 58960,
      "duration": 320,
      "noteType": "Weapon1",
      "abilityId": 5500
    },
    {
      "time": 59280,
      "duration": 912,
      "noteType": "Weapon3",
      "abilityId": 42954
    },
    {
      "time": 60192,
      "duration": 1008,
      "noteType": "Weapon1",
      "abilityId": 5500
    },
    {
      "time": 60560,
      "duration": 0,
      "noteType": "Profession1",
      "abilityId": -7
    },
    {
      "time": 61200,
      "duration": 672,
      "noteType": "Weapon2",
      "abilityId": 5692
    },
    {
      "time": 61872,
      "duration": 528,
      "noteType": "Utility2",
      "abilityId": 5542
    },
    {
      "time": 62400,
      "duration": 592,
      "noteType": "Weapon1",
      "abilityId": 5508
    },
    {
      "time": 62992,
      "duration": 608,
      "noteType": "Weapon1",
      "abilityId": 5508
    },
    {
      "time": 63600,
      "duration": 592,
      "noteType": "Weapon1",
      "abilityId": 5508
    },
    {
      "time": 63840,
      "duration": 0,
      "noteType": "Profession1",
      "abilityId": 43470
    },
    {
      "time": 64192,
      "duration": 48,
      "noteType": "Weapon1",
      "abilityId": 5508
    },
    {
      "time": 64240,
      "duration": 480,
      "noteType": "Weapon3",
      "abilityId": 5675
    },
    {
      "time": 64720,
      "duration": 352,
      "noteType": "Weapon5",
      "abilityId": 51711
    },
    {
      "time": 65072,
      "duration": 560,
      "noteType": "Weapon4",
      "abilityId": 5497
    },
    {
      "time": 65632,
      "duration": 608,
      "noteType": "Weapon1",
      "abilityId": 5508
    },
    {
      "time": 66240,
      "duration": 592,
      "noteType": "Weapon1",
      "abilityId": 5508
    },
    {
      "time": 66832,
      "duration": 528,
      "noteType": "Weapon1",
      "abilityId": 5508
    },
    {
      "time": 67360,
      "duration": 672,
      "noteType": "Weapon2",
      "abilityId": 5692
    },
    {
      "time": 67552,
      "duration": 0,
      "noteType": "Profession4",
      "abilityId": -14
    },
    {
      "time": 68032,
      "duration": 768,
      "noteType": "Weapon2",
      "abilityId": 5695
    },
    {
      "time": 68791,
      "duration": 0,
      "noteType": "Weapon2",
      "abilityId": 5780
    },
    {
      "time": 68800,
      "duration": 1120,
      "noteType": "Weapon1",
      "abilityId": 5500
    },
    {
      "time": 69920,
      "duration": 913,
      "noteType": "Weapon3",
      "abilityId": 42954
    },
    {
      "time": 70832,
      "duration": 0,
      "noteType": "Profession1",
      "abilityId": -7
    },
    {
      "time": 70833,
      "duration": 607,
      "noteType": "Weapon1",
      "abilityId": 5508
    },
    {
      "time": 71440,
      "duration": 592,
      "noteType": "Weapon1",
      "abilityId": 5508
    },
    {
      "time": 72032,
      "duration": 48,
      "noteType": "Weapon1",
      "abilityId": 5508
    },
    {
      "time": 72080,
      "duration": 512,
      "noteType": "Utility2",
      "abilityId": 5542
    },
    {
      "time": 72592,
      "duration": 688,
      "noteType": "Weapon2",
      "abilityId": 5692
    },
    {
      "time": 73280,
      "duration": 592,
      "noteType": "Weapon1",
      "abilityId": 5508
    },
    {
      "time": 73872,
      "duration": 608,
      "noteType": "Weapon1",
      "abilityId": 5508
    },
    {
      "time": 74192,
      "duration": 0,
      "noteType": "Profession1",
      "abilityId": 43470
    },
    {
      "time": 74480,
      "duration": 400,
      "noteType": "Weapon1",
      "abilityId": 5508
    },
    {
      "time": 74880,
      "duration": 480,
      "noteType": "Weapon3",
      "abilityId": 5675
    },
    {
      "time": 75360,
      "duration": 352,
      "noteType": "Weapon5",
      "abilityId": 51711
    },
    {
      "time": 75712,
      "duration": 608,
      "noteType": "Weapon1",
      "abilityId": 5508
    },
    {
      "time": 76320,
      "duration": 592,
      "noteType": "Weapon1",
      "abilityId": 5508
    },
    {
      "time": 76912,
      "duration": 368,
      "noteType": "Weapon1",
      "abilityId": 5508
    },
    {
      "time": 77280,
      "duration": 688,
      "noteType": "Weapon2",
      "abilityId": 5692
    },
    {
      "time": 77712,
      "duration": 0,
      "noteType": "Profession4",
      "abilityId": -14
    },
    {
      "time": 77968,
      "duration": 32,
      "noteType": "Weapon1",
      "abilityId": 5500
    },
    {
      "time": 78000,
      "duration": 752,
      "noteType": "Weapon2",
      "abilityId": 5695
    },
    {
      "time": 78720,
      "duration": 0,
      "noteType": "Utility3",
      "abilityId": 40183
    },
    {
      "time": 78752,
      "duration": 448,
      "noteType": "Weapon1",
      "abilityId": 5500
    },
    {
      "time": 78759,
      "duration": 0,
      "noteType": "Weapon2",
      "abilityId": 5780
    },
    {
      "time": 79200,
      "duration": 560,
      "noteType": "Weapon4",
      "abilityId": 5497
    },
    {
      "time": 79760,
      "duration": 752,
      "noteType": "Weapon1",
      "abilityId": 5500
    },
    {
      "time": 80512,
      "duration": 928,
      "noteType": "Weapon3",
      "abilityId": 42954
    },
    {
      "time": 81440,
      "duration": 1088,
      "noteType": "Weapon1",
      "abilityId": 5500
    },
    {
      "time": 81600,
      "duration": 0,
      "noteType": "Profession1",
      "abilityId": -7
    },
    {
      "time": 82528,
      "duration": 512,
      "noteType": "Utility2",
      "abilityId": 5542
    },
    {
      "time": 83040,
      "duration": 672,
      "noteType": "Weapon2",
      "abilityId": 5692
    },
    {
      "time": 83712,
      "duration": 608,
      "noteType": "Weapon1",
      "abilityId": 5508
    },
    {
      "time": 84320,
      "duration": 592,
      "noteType": "Weapon1",
      "abilityId": 5508
    },
    {
      "time": 84912,
      "duration": 480,
      "noteType": "Weapon1",
      "abilityId": 5508
    },
    {
      "time": 84992,
      "duration": 0,
      "noteType": "Profession1",
      "abilityId": 43470
    },
    {
      "time": 85392,
      "duration": 496,
      "noteType": "Weapon3",
      "abilityId": 5675
    },
    {
      "time": 85888,
      "duration": 352,
      "noteType": "Weapon5",
      "abilityId": 51711
    },
    {
      "time": 86240,
      "duration": 592,
      "noteType": "Weapon1",
      "abilityId": 5508
    },
    {
      "time": 86832,
      "duration": 608,
      "noteType": "Weapon1",
      "abilityId": 5508
    },
    {
      "time": 87440,
      "duration": 592,
      "noteType": "Weapon1",
      "abilityId": 5508
    },
    {
      "time": 88032,
      "duration": 208,
      "noteType": "Weapon1",
      "abilityId": 5508
    },
    {
      "time": 88240,
      "duration": 672,
      "noteType": "Weapon2",
      "abilityId": 5692
    },
    {
      "time": 88480,
      "duration": 0,
      "noteType": "Profession4",
      "abilityId": -14
    },
    {
      "time": 88912,
      "duration": 768,
      "noteType": "Weapon2",
      "abilityId": 5695
    },
    {
      "time": 89120,
      "duration": 0,
      "noteType": "Utility3",
      "abilityId": 40183
    },
    {
      "time": 89671,
      "duration": 0,
      "noteType": "Weapon2",
      "abilityId": 5780
    },
    {
      "time": 89680,
      "duration": 1392,
      "noteType": "Weapon1",
      "abilityId": 5500
    },
    {
      "time": 91072,
      "duration": 80,
      "noteType": "Weapon1",
      "abilityId": 5500
    },
    {
      "time": 91152,
      "duration": 928,
      "noteType": "Weapon3",
      "abilityId": 42954
    },
    {
      "time": 92080,
      "duration": 720,
      "noteType": "Weapon1",
      "abilityId": 5500
    },
    {
      "time": 92112,
      "duration": 0,
      "noteType": "Profession1",
      "abilityId": -7
    },
    {
      "time": 92800,
      "duration": 672,
      "noteType": "Weapon2",
      "abilityId": 5692
    },
    {
      "time": 93472,
      "duration": 528,
      "noteType": "Utility2",
      "abilityId": 5542
    },
    {
      "time": 94000,
      "duration": 592,
      "noteType": "Weapon1",
      "abilityId": 5508
    },
    {
      "time": 94592,
      "duration": 608,
      "noteType": "Weapon1",
      "abilityId": 5508
    },
    {
      "time": 95200,
      "duration": 592,
      "noteType": "Weapon1",
      "abilityId": 5508
    },
    {
      "time": 95712,
      "duration": 0,
      "noteType": "Profession1",
      "abilityId": 43470
    },
    {
      "time": 95792,
      "duration": 288,
      "noteType": "Weapon1",
      "abilityId": 5508
    },
    {
      "time": 96080,
      "duration": 480,
      "noteType": "Weapon3",
      "abilityId": 5675
    },
    {
      "time": 96560,
      "duration": 352,
      "noteType": "Weapon5",
      "abilityId": 51711
    },
    {
      "time": 96912,
      "duration": 80,
      "noteType": "Weapon1",
      "abilityId": 5508
    },
    {
      "time": 96992,
      "duration": 560,
      "noteType": "Weapon4",
      "abilityId": 5497
    },
    {
      "time": 97552,
      "duration": 608,
      "noteType": "Weapon1",
      "abilityId": 5508
    },
    {
      "time": 98160,
      "duration": 592,
      "noteType": "Weapon1",
      "abilityId": 5508
    },
    {
      "time": 98752,
      "duration": 80,
      "noteType": "Weapon1",
      "abilityId": 5508
    },
    {
      "time": 98832,
      "duration": 688,
      "noteType": "Weapon2",
      "abilityId": 5692
    },
    {
      "time": 99200,
      "duration": 0,
      "noteType": "Profession4",
      "abilityId": -14
    },
    {
      "time": 99520,
      "duration": 768,
      "noteType": "Weapon2",
      "abilityId": 5695
    },
    {
      "time": 100279,
      "duration": 0,
      "noteType": "Weapon2",
      "abilityId": 5780
    },
    {
      "time": 100288,
      "duration": 1392,
      "noteType": "Weapon1",
      "abilityId": 5500
    },
    {
      "time": 101680,
      "duration": 400,
      "noteType": "Weapon1",
      "abilityId": 5500
    },
    {
      "time": 102080,
      "duration": 912,
      "noteType": "Weapon3",
      "abilityId": 42954
    },
    {
      "time": 102720,
      "duration": 0,
      "noteType": "Profession1",
      "abilityId": -7
    },
    {
      "time": 102992,
      "duration": 496,
      "noteType": "Weapon1",
      "abilityId": 5508
    },
    {
      "time": 103488,
      "duration": 672,
      "noteType": "Weapon2",
      "abilityId": 5692
    },
    {
      "time": 104160,
      "duration": 512,
      "noteType": "Utility2",
      "abilityId": 5542
    },
    {
      "time": 104672,
      "duration": 608,
      "noteType": "Weapon1",
      "abilityId": 5508
    },
    {
      "time": 105280,
      "duration": 592,
      "noteType": "Weapon1",
      "abilityId": 5508
    },
    {
      "time": 105872,
      "duration": 640,
      "noteType": "Weapon1",
      "abilityId": 5508
    },
    {
      "time": 106112,
      "duration": 0,
      "noteType": "Profession1",
      "abilityId": 43470
    },
    {
      "time": 106512,
      "duration": 480,
      "noteType": "Weapon3",
      "abilityId": 5675
    },
    {
      "time": 106992,
      "duration": 368,
      "noteType": "Weapon5",
      "abilityId": 51711
    },
    {
      "time": 107360,
      "duration": 608,
      "noteType": "Weapon1",
      "abilityId": 5508
    },
    {
      "time": 107680,
      "duration": 0,
      "noteType": "Utility3",
      "abilityId": 40183
    },
    {
      "time": 107968,
      "duration": 160,
      "noteType": "Weapon1",
      "abilityId": 5508
    },
    {
      "time": 108128,
      "duration": 672,
      "noteType": "Weapon2",
      "abilityId": 5692
    },
    {
      "time": 108800,
      "duration": 992,
      "noteType": "Weapon1",
      "abilityId": 5508
    }
  ]
}