{
  "name": "Condition Weaver [SC]",
  "description": "Build and rotation created by Snow Crows.\n\nPublished Jul 20, 2022\nUpdated Sep 4, 2023\nSecrets of the Obscure",
  "logUrl": "https://dps.report/Rh4G-20230831-184205_golem",
  "buildChatCode": "[&DQYfFRomOBV0AAAAcwAAAMsAAAA1FwAAEhcAAAAAAAAAAAAAAAAAAAAAAAA=]",
  "buildUrl": "https://snowcrows.com/en/builds/elementalist/weaver/condition-weaver",
  "decodedBuildTemplate": {
    "profession": 6,
    "specializations": [
      {
        "id": 31,
        "traits": [
          1,
          1,
          1
        ]
      },
      {
        "id": 26,
        "traits": [
          2,
          1,
          2
        ]
      },
      {
        "id": 56,
        "traits": [
          1,
          1,
          1
        ]
      }
    ],
    "skills": {
      "terrestrial": {
        "heal": 116,
        "utilities": [
          115,
          203,
          5941
        ],
        "elite": 5906
      },
      "aquatic": {
        "heal": 0,
        "utilities": [
          0,
          0,
          0
        ],
        "elite": 0
      }
    },
    "specific": [
      0,
      0,
      0,
      0,
      0,
      0,
      0,
      0,
      0,
      0,
      0,
      0,
      0,
      0,
      0,
      0
    ]
  },
  "notes": [
    {
      "time": 0,
      "duration": 800,
      "noteType": "Elite",
      "abilityId": 43638
    },
    {
      "time": 200,
      "duration": 518,
      "noteType": "Utility2",
      "abilityId": 5542
    },
    {
      "time": 1000,
      "duration": 842,
      "noteType": "Weapon5",
      "abilityId": 29533
    },
    {
      "time": 1518,
      "duration": 0,
      "noteType": "Profession1",
      "abilityId": -6
    },
    {
      "time": 1519,
      "duration": 0,
      "noteType": "Weapon2",
      "abilityId": 5561
    },
    {
      "time": 1559,
      "duration": 0,
      "noteType": "Utility3",
      "abilityId": 40183
    },
    {
      "time": 2160,
      "duration": 677,
      "noteType": "Weapon2",
      "abilityId": 5692
    },
    {
      "time": 2360,
      "duration": 440,
      "noteType": "Weapon5",
      "abilityId": 30795
    },
    {
      "time": 3201,
      "duration": 0,
      "noteType": "Profession1",
      "abilityId": 43470
    },
    {
      "time": 3277,
      "duration": 480,
      "noteType": "Weapon3",
      "abilityId": 5675
    },
    {
      "time": 3757,
      "duration": 600,
      "noteType": "Weapon1",
      "abilityId": 5508
    },
    {
      "time": 4357,
      "duration": 600,
      "noteType": "Weapon1",
      "abilityId": 5508
    },
    {
      "time": 4878,
      "duration": 0,
      "noteType": "Profession4",
      "abilityId": -14
    },
    {
      "time": 4957,
      "duration": 81,
      "noteType": "Weapon1",
      "abilityId": 5500
    },
    {
      "time": 5038,
      "duration": 920,
      "noteType": "Weapon3",
      "abilityId": 42954
    },
    {
      "time": 5718,
      "duration": 0,
      "noteType": "Utility3",
      "abilityId": 40183
    },
    {
      "time": 5958,
      "duration": 800,
      "noteType": "Weapon1",
      "abilityId": 5500
    },
    {
      "time": 6602,
      "duration": 0,
      "noteType": "Profession1",
      "abilityId": -7
    },
    {
      "time": 6758,
      "duration": 841,
      "noteType": "Weapon5",
      "abilityId": 30336
    },
    {
      "time": 6958,
      "duration": 680,
      "noteType": "Weapon2",
      "abilityId": 5692
    },
    {
      "time": 8279,
      "duration": 600,
      "noteType": "Weapon1",
      "abilityId": 5508
    },
    {
      "time": 8399,
      "duration": 0,
      "noteType": "Profession1",
      "abilityId": 43470
    },
    {
      "time": 8879,
      "duration": 600,
      "noteType": "Weapon1",
      "abilityId": 5508
    },
    {
      "time": 9479,
      "duration": 600,
      "noteType": "Weapon1",
      "abilityId": 5508
    },
    {
      "time": 10079,
      "duration": 600,
      "noteType": "Weapon1",
      "abilityId": 5508
    },
    {
      "time": 10679,
      "duration": 40,
      "noteType": "Weapon1",
      "abilityId": 5508
    },
    {
      "time": 10719,
      "duration": 480,
      "noteType": "Weapon3",
      "abilityId": 5675
    },
    {
      "time": 10839,
      "duration": 0,
      "noteType": "Profession4",
      "abilityId": -14
    },
    {
      "time": 11199,
      "duration": 521,
      "noteType": "Utility2",
      "abilityId": 5542
    },
    {
      "time": 11399,
      "duration": 761,
      "noteType": "Weapon2",
      "abilityId": 5695
    },
    {
      "time": 12479,
      "duration": 0,
      "noteType": "Weapon2",
      "abilityId": 5780
    },
    {
      "time": 12481,
      "duration": 360,
      "noteType": "Weapon1",
      "abilityId": 5500
    },
    {
      "time": 12721,
      "duration": 0,
      "noteType": "Profession1",
      "abilityId": -7
    },
    {
      "time": 12757,
      "duration": 0,
      "noteType": "Utility1",
      "abilityId": 34736
    },
    {
      "time": 12841,
      "duration": 678,
      "noteType": "Weapon2",
      "abilityId": 5692
    },
    {
      "time": 13519,
      "duration": 601,
      "noteType": "Weapon1",
      "abilityId": 5508
    },
    {
      "time": 14120,
      "duration": 600,
      "noteType": "Weapon1",
      "abilityId": 5508
    },
    {
      "time": 14440,
      "duration": 0,
      "noteType": "Profession1",
      "abilityId": 43470
    },
    {
      "time": 14720,
      "duration": 608,
      "noteType": "Weapon1",
      "abilityId": 5508
    },
    {
      "time": 15328,
      "duration": 592,
      "noteType": "Weapon1",
      "abilityId": 5508
    },
    {
      "time": 15920,
      "duration": 600,
      "noteType": "Weapon1",
      "abilityId": 5508
    },
    {
      "time": 16520,
      "duration": 601,
      "noteType": "Weapon1",
      "abilityId": 5508
    },
    {
      "time": 17121,
      "duration": 598,
      "noteType": "Weapon1",
      "abilityId": 5508
    },
    {
      "time": 17719,
      "duration": 680,
      "noteType": "Weapon2",
      "abilityId": 5692
    },
    {
      "time": 17919,
      "duration": 480,
      "noteType": "Weapon3",
      "abilityId": 5675
    },
    {
      "time": 18603,
      "duration": 0,
      "noteType": "Profession4",
      "abilityId": -14
    },
    {
      "time": 18879,
      "duration": 759,
      "noteType": "Weapon2",
      "abilityId": 5695
    },
    {
      "time": 19638,
      "duration": 40,
      "noteType": "Weapon1",
      "abilityId": 5500
    },
    {
      "time": 19638,
      "duration": 0,
      "noteType": "Weapon2",
      "abilityId": 5780
    },
    {
      "time": 19678,
      "duration": 921,
      "noteType": "Weapon3",
      "abilityId": 42954
    },
    {
      "time": 20362,
      "duration": 0,
      "noteType": "Profession2",
      "abilityId": -10
    },
    {
      "time": 20599,
      "duration": 600,
      "noteType": "Weapon3",
      "abilityId": 46014
    },
    {
      "time": 20799,
      "duration": 402,
      "noteType": "Weapon2",
      "abilityId": 5538
    },
    {
      "time": 21399,
      "duration": 516,
      "noteType": "Utility2",
      "abilityId": 5542
    },
    {
      "time": 22081,
      "duration": 0,
      "noteType": "Profession1",
      "abilityId": -5
    },
    {
      "time": 22117,
      "duration": 604,
      "noteType": "Weapon1",
      "abilityId": 5508
    },
    {
      "time": 22721,
      "duration": 676,
      "noteType": "Weapon2",
      "abilityId": 5692
    },
    {
      "time": 23397,
      "duration": 601,
      "noteType": "Weapon1",
      "abilityId": 5508
    },
    {
      "time": 23998,
      "duration": 600,
      "noteType": "Weapon1",
      "abilityId": 5508
    },
    {
      "time": 24598,
      "duration": 600,
      "noteType": "Weapon1",
      "abilityId": 5508
    },
    {
      "time": 25198,
      "duration": 602,
      "noteType": "Weapon1",
      "abilityId": 5508
    },
    {
      "time": 25520,
      "duration": 0,
      "noteType": "Profession1",
      "abilityId": 43470
    },
    {
      "time": 25800,
      "duration": 480,
      "noteType": "Weapon3",
      "abilityId": 5675
    },
    {
      "time": 26000,
      "duration": 841,
      "noteType": "Weapon5",
      "abilityId": 29533
    },
    {
      "time": 27121,
      "duration": 596,
      "noteType": "Weapon1",
      "abilityId": 5508
    },
    {
      "time": 27717,
      "duration": 601,
      "noteType": "Weapon1",
      "abilityId": 5508
    },
    {
      "time": 28318,
      "duration": 640,
      "noteType": "Weapon1",
      "abilityId": 5508
    },
    {
      "time": 28918,
      "duration": 0,
      "noteType": "Utility3",
      "abilityId": 40183
    },
    {
      "time": 28958,
      "duration": 679,
      "noteType": "Weapon2",
      "abilityId": 5692
    },
    {
      "time": 29078,
      "duration": 0,
      "noteType": "Profession4",
      "abilityId": -14
    },
    {
      "time": 29637,
      "duration": 841,
      "noteType": "Weapon2",
      "abilityId": 5695
    },
    {
      "time": 29837,
      "duration": 920,
      "noteType": "Weapon3",
      "abilityId": 42954
    },
    {
      "time": 30396,
      "duration": 0,
      "noteType": "Weapon2",
      "abilityId": 5780
    },
    {
      "time": 31398,
      "duration": 520,
      "noteType": "Weapon1",
      "abilityId": 5500
    },
    {
      "time": 31918,
      "duration": 520,
      "noteType": "Utility2",
      "abilityId": 5542
    },
    {
      "time": 32362,
      "duration": 0,
      "noteType": "Profession1",
      "abilityId": -7
    },
    {
      "time": 32438,
      "duration": 840,
      "noteType": "Weapon5",
      "abilityId": 30336
    },
    {
      "time": 32838,
      "duration": 0,
      "noteType": "Utility1",
      "abilityId": 34736
    },
    {
      "time": 33277,
      "duration": 602,
      "noteType": "Weapon1",
      "abilityId": 5508
    },
    {
      "time": 33880,
      "duration": 680,
      "noteType": "Weapon2",
      "abilityId": 5692
    },
    {
      "time": 34560,
      "duration": 600,
      "noteType": "Weapon1",
      "abilityId": 5508
    },
    {
      "time": 35160,
      "duration": 600,
      "noteType": "Weapon1",
      "abilityId": 5508
    },
    {
      "time": 35720,
      "duration": 0,
      "noteType": "Profession1",
      "abilityId": 43470
    },
    {
      "time": 35760,
      "duration": 40,
      "noteType": "Weapon1",
      "abilityId": 5508
    },
    {
      "time": 35800,
      "duration": 480,
      "noteType": "Weapon3",
      "abilityId": 5675
    },
    {
      "time": 36280,
      "duration": 600,
      "noteType": "Weapon1",
      "abilityId": 5508
    },
    {
      "time": 36880,
      "duration": 598,
      "noteType": "Weapon1",
      "abilityId": 5508
    },
    {
      "time": 37478,
      "duration": 601,
      "noteType": "Weapon1",
      "abilityId": 5508
    },
    {
      "time": 38079,
      "duration": 640,
      "noteType": "Weapon1",
      "abilityId": 5508
    },
    {
      "time": 38599,
      "duration": 0,
      "noteType": "Utility3",
      "abilityId": 40183
    },
    {
      "time": 38719,
      "duration": 680,
      "noteType": "Weapon2",
      "abilityId": 5692
    },
    {
      "time": 38959,
      "duration": 0,
      "noteType": "Profession4",
      "abilityId": -14
    },
    {
      "time": 39399,
      "duration": 760,
      "noteType": "Weapon2",
      "abilityId": 5695
    },
    {
      "time": 40158,
      "duration": 0,
      "noteType": "Weapon2",
      "abilityId": 5780
    },
    {
      "time": 40159,
      "duration": 1001,
      "noteType": "Weapon1",
      "abilityId": 5500
    },
    {
      "time": 41160,
      "duration": 919,
      "noteType": "Weapon3",
      "abilityId": 42954
    },
    {
      "time": 42079,
      "duration": 40,
      "noteType": "Weapon1",
      "abilityId": 5500
    },
    {
      "time": 42119,
      "duration": 520,
      "noteType": "Utility2",
      "abilityId": 5542
    },
    {
      "time": 42279,
      "duration": 0,
      "noteType": "Profession1",
      "abilityId": -7
    },
    {
      "time": 42639,
      "duration": 600,
      "noteType": "Weapon1",
      "abilityId": 5508
    },
    {
      "time": 43239,
      "duration": 120,
      "noteType": "Weapon1",
      "abilityId": 5508
    },
    {
      "time": 43359,
      "duration": 681,
      "noteType": "Weapon2",
      "abilityId": 5692
    },
    {
      "time": 44040,
      "duration": 600,
      "noteType": "Weapon1",
      "abilityId": 5508
    },
    {
      "time": 44640,
      "duration": 600,
      "noteType": "Weapon1",
      "abilityId": 5508
    },
    {
      "time": 45240,
      "duration": 600,
      "noteType": "Weapon1",
      "abilityId": 5508
    },
    {
      "time": 45600,
      "duration": 0,
      "noteType": "Profession1",
      "abilityId": 43470
    },
    {
      "time": 45840,
      "duration": 478,
      "noteType": "Weapon3",
      "abilityId": 5675
    },
    {
      "time": 46318,
      "duration": 641,
      "noteType": "Weapon1",
      "abilityId": 5508
    },
    {
      "time": 46959,
      "duration": 841,
      "noteType": "Weapon5",
      "abilityId": 29533
    },
    {
      "time": 47800,
      "duration": 600,
      "noteType": "Weapon1",
      "abilityId": 5508
    },
    {
      "time": 48400,
      "duration": 600,
      "noteType": "Weapon1",
      "abilityId": 5508
    },
    {
      "time": 49000,
      "duration": 640,
      "noteType": "Weapon1",
      "abilityId": 5508
    },
    {
      "time": 49640,
      "duration": 678,
      "noteType": "Weapon2",
      "abilityId": 5692
    },
    {
      "time": 49680,
      "duration": 0,
      "noteType": "Profession4",
      "abilityId": -14
    },
    {
      "time": 50318,
      "duration": 760,
      "noteType": "Weapon2",
      "abilityId": 5695
    },
    {
      "time": 51077,
      "duration": 0,
      "noteType": "Weapon2",
      "abilityId": 5780
    },
    {
      "time": 51078,
      "duration": 760,
      "noteType": "Weapon1",
      "abilityId": 5500
    },
    {
      "time": 51838,
      "duration": 960,
      "noteType": "Weapon3",
      "abilityId": 42954
    },
    {
      "time": 52038,
      "duration": 520,
      "noteType": "Utility2",
      "abilityId": 5542
    },
    {
      "time": 53198,
      "duration": 0,
      "noteType": "Profession1",
      "abilityId": -7
    },
    {
      "time": 53318,
      "duration": 80,
      "noteType": "Weapon1",
      "abilityId": 5508
    },
    {
      "time": 53358,
      "duration": 0,
      "noteType": "Utility1",
      "abilityId": 34736
    },
    {
      "time": 53398,
      "duration": 840,
      "noteType": "Weapon5",
      "abilityId": 30336
    },
    {
      "time": 54238,
      "duration": 602,
      "noteType": "Weapon1",
      "abilityId": 5508
    },
    {
      "time": 54840,
      "duration": 680,
      "noteType": "Weapon2",
      "abilityId": 5692
    },
    {
      "time": 55520,
      "duration": 597,
      "noteType": "Weapon1",
      "abilityId": 5508
    },
    {
      "time": 56117,
      "duration": 641,
      "noteType": "Weapon1",
      "abilityId": 5508
    },
    {
      "time": 56438,
      "duration": 0,
      "noteType": "Profession1",
      "abilityId": 43470
    },
    {
      "time": 56758,
      "duration": 480,
      "noteType": "Weapon3",
      "abilityId": 5675
    },
    {
      "time": 57238,
      "duration": 600,
      "noteType": "Weapon1",
      "abilityId": 5508
    },
    {
      "time": 57838,
      "duration": 600,
      "noteType": "Weapon1",
      "abilityId": 5508
    },
    {
      "time": 58438,
      "duration": 602,
      "noteType": "Weapon1",
      "abilityId": 5508
    },
    {
      "time": 59040,
      "duration": 640,
      "noteType": "Weapon1",
      "abilityId": 5508
    },
    {
      "time": 59680,
      "duration": 677,
      "noteType": "Weapon2",
      "abilityId": 5692
    },
    {
      "time": 59840,
      "duration": 0,
      "noteType": "Profession4",
      "abilityId": -14
    },
    {
      "time": 60157,
      "duration": 0,
      "noteType": "Utility3",
      "abilityId": 40183
    },
    {
      "time": 60357,
      "duration": 764,
      "noteType": "Weapon2",
      "abilityId": 5695
    },
    {
      "time": 61116,
      "duration": 0,
      "noteType": "Weapon2",
      "abilityId": 5780
    },
    {
      "time": 61121,
      "duration": 1357,
      "noteType": "Weapon1",
      "abilityId": 5500
    },
    {
      "time": 62478,
      "duration": 922,
      "noteType": "Weapon3",
      "abilityId": 42954
    },
    {
      "time": 63280,
      "duration": 0,
      "noteType": "Profession1",
      "abilityId": -7
    },
    {
      "time": 63400,
      "duration": 520,
      "noteType": "Utility2",
      "abilityId": 5542
    },
    {
      "time": 63920,
      "duration": 640,
      "noteType": "Weapon1",
      "abilityId": 5508
    },
    {
      "time": 64560,
      "duration": 680,
      "noteType": "Weapon2",
      "abilityId": 5692
    },
    {
      "time": 65240,
      "duration": 600,
      "noteType": "Weapon1",
      "abilityId": 5508
    },
    {
      "time": 65839,
      "duration": 600,
      "noteType": "Weapon1",
      "abilityId": 5508
    },
    {
      "time": 66440,
      "duration": 641,
      "noteType": "Weapon1",
      "abilityId": 5508
    },
    {
      "time": 66680,
      "duration": 0,
      "noteType": "Profession1",
      "abilityId": 43470
    },
    {
      "time": 67081,
      "duration": 477,
      "noteType": "Weapon3",
      "abilityId": 5675
    },
    {
      "time": 67281,
      "duration": 842,
      "noteType": "Weapon5",
      "abilityId": 29533
    },
    {
      "time": 68400,
      "duration": 600,
      "noteType": "Weapon1",
      "abilityId": 5508
    },
    {
      "time": 69000,
      "duration": 600,
      "noteType": "Weapon1",
      "abilityId": 5508
    },
    {
      "time": 69600,
      "duration": 600,
      "noteType": "Weapon1",
      "abilityId": 5508
    },
    {
      "time": 70200,
      "duration": 640,
      "noteType": "Weapon1",
      "abilityId": 5508
    },
    {
      "time": 70840,
      "duration": 682,
      "noteType": "Weapon2",
      "abilityId": 5692
    },
    {
      "time": 70922,
      "duration": 0,
      "noteType": "Profession3",
      "abilityId": -11
    },
    {
      "time": 71522,
      "duration": 916,
      "noteType": "Weapon3",
      "abilityId": 43576
    },
    {
      "time": 72438,
      "duration": 484,
      "noteType": "Weapon1",
      "abilityId": 5526
    },
    {
      "time": 72922,
      "duration": 800,
      "noteType": "Elite",
      "abilityId": 43638
    },
    {
      "time": 73122,
      "duration": 756,
      "noteType": "Utility2",
      "abilityId": 5542
    },
    {
      "time": 74278,
      "duration": 0,
      "noteType": "Weapon2",
      "abilityId": 5561
    },
    {
      "time": 74402,
      "duration": 0,
      "noteType": "Profession1",
      "abilityId": -6
    },
    {
      "time": 74478,
      "duration": 440,
      "noteType": "Weapon5",
      "abilityId": 30795
    },
    {
      "time": 74598,
      "duration": 0,
      "noteType": "Utility1",
      "abilityId": 34736
    },
    {
      "time": 74918,
      "duration": 603,
      "noteType": "Weapon1",
      "abilityId": 5508
    },
    {
      "time": 75362,
      "duration": 0,
      "noteType": "Utility3",
      "abilityId": 40183
    },
    {
      "time": 75521,
      "duration": 40,
      "noteType": "Weapon1",
      "abilityId": 5508
    },
    {
      "time": 75561,
      "duration": 680,
      "noteType": "Weapon2",
      "abilityId": 5692
    },
    {
      "time": 76201,
      "duration": 0,
      "noteType": "Profession1",
      "abilityId": 43470
    },
    {
      "time": 76241,
      "duration": 40,
      "noteType": "Weapon1",
      "abilityId": 5508
    },
    {
      "time": 76281,
      "duration": 480,
      "noteType": "Weapon3",
      "abilityId": 5675
    },
    {
      "time": 76761,
      "duration": 601,
      "noteType": "Weapon1",
      "abilityId": 5508
    },
    {
      "time": 77362,
      "duration": 598,
      "noteType": "Weapon1",
      "abilityId": 5508
    },
    {
      "time": 77879,
      "duration": 0,
      "noteType": "Profession4",
      "abilityId": -14
    },
    {
      "time": 77960,
      "duration": 120,
      "noteType": "Weapon1",
      "abilityId": 5500
    },
    {
      "time": 78080,
      "duration": 760,
      "noteType": "Weapon2",
      "abilityId": 5695
    },
    {
      "time": 78839,
      "duration": 0,
      "noteType": "Weapon2",
      "abilityId": 5780
    },
    {
      "time": 78840,
      "duration": 120,
      "noteType": "Weapon1",
      "abilityId": 5500
    },
    {
      "time": 78960,
      "duration": 920,
      "noteType": "Weapon3",
      "abilityId": 42954
    },
    {
      "time": 79560,
      "duration": 0,
      "noteType": "Profession1",
      "abilityId": -7
    },
    {
      "time": 79880,
      "duration": 840,
      "noteType": "Weapon5",
      "abilityId": 30336
    },
    {
      "time": 80080,
      "duration": 678,
      "noteType": "Weapon2",
      "abilityId": 5692
    },
    {
      "time": 81282,
      "duration": 0,
      "noteType": "Profession1",
      "abilityId": 43470
    },
    {
      "time": 81398,
      "duration": 604,
      "noteType": "Weapon1",
      "abilityId": 5508
    },
    {
      "time": 81758,
      "duration": 0,
      "noteType": "Utility3",
      "abilityId": 40183
    },
    {
      "time": 82002,
      "duration": 596,
      "noteType": "Weapon1",
      "abilityId": 5508
    },
    {
      "time": 82598,
      "duration": 602,
      "noteType": "Weapon1",
      "abilityId": 5508
    },
    {
      "time": 83200,
      "duration": 40,
      "noteType": "Weapon1",
      "abilityId": 5508
    },
    {
      "time": 83240,
      "duration": 480,
      "noteType": "Weapon3",
      "abilityId": 5675
    },
    {
      "time": 83440,
      "duration": 0,
      "noteType": "Profession4",
      "abilityId": -14
    },
    {
      "time": 83720,
      "duration": 480,
      "noteType": "Weapon1",
      "abilityId": 5500
    },
    {
      "time": 84200,
      "duration": 519,
      "noteType": "Utility2",
      "abilityId": 5542
    },
    {
      "time": 84400,
      "duration": 760,
      "noteType": "Weapon2",
      "abilityId": 5695
    },
    {
      "time": 85163,
      "duration": 0,
      "noteType": "Profession1",
      "abilityId": -7
    },
    {
      "time": 85478,
      "duration": 0,
      "noteType": "Weapon2",
      "abilityId": 5780
    },
    {
      "time": 85479,
      "duration": 680,
      "noteType": "Weapon2",
      "abilityId": 5692
    },
    {
      "time": 86159,
      "duration": 600,
      "noteType": "Weapon1",
      "abilityId": 5508
    },
    {
      "time": 86759,
      "duration": 602,
      "noteType": "Weapon1",
      "abilityId": 5508
    },
    {
      "time": 86961,
      "duration": 0,
      "noteType": "Profession1",
      "abilityId": 43470
    },
    {
      "time": 87361,
      "duration": 600,
      "noteType": "Weapon1",
      "abilityId": 5508
    },
    {
      "time": 87961,
      "duration": 601,
      "noteType": "Weapon1",
      "abilityId": 5508
    },
    {
      "time": 88562,
      "duration": 596,
      "noteType": "Weapon1",
      "abilityId": 5508
    },
    {
      "time": 89158,
      "duration": 600,
      "noteType": "Weapon1",
      "abilityId": 5508
    },
    {
      "time": 89758,
      "duration": 604,
      "noteType": "Weapon1",
      "abilityId": 5508
    },
    {
      "time": 90362,
      "duration": 76,
      "noteType": "Weapon1",
      "abilityId": 5508
    },
    {
      "time": 90438,
      "duration": 480,
      "noteType": "Weapon3",
      "abilityId": 5675
    },
    {
      "time": 90722,
      "duration": 0,
      "noteType": "Profession4",
      "abilityId": -14
    },
    {
      "time": 90918,
      "duration": 1002,
      "noteType": "Weapon1",
      "abilityId": 5500
    }
  ]
}