{
  "name": "Condition Quickness Harbinger [SC]",
  "description": "",
  "logUrl": "https://dps.report/9GSF-20231002-152522_golem",
  "buildChatCode": "[&DQgnNTI1QCvnGgAAgAAAAHUBAADsGgAA6BoAAAAAAAAAAAAAAAAAAAAAAAA=]",
  "buildUrl": "https://snowcrows.com/builds/raids/necromancer/condition-quickness-harbinger",
  "decodedBuildTemplate": {
    "profession": 8,
    "specializations": [
      {
        "id": 39,
        "traits": [
          1,
          1,
          3
        ]
      },
      {
        "id": 50,
        "traits": [
          1,
          1,
          3
        ]
      },
      {
        "id": 64,
        "traits": [
          3,
          2,
          2
        ]
      }
    ],
    "skills": {
      "terrestrial": {
        "heal": 6887,
        "utilities": [
          128,
          373,
          6892
        ],
        "elite": 6888
      },
      "aquatic": {
        "heal": 0,
        "utilities": [
          0,
          0,
          0
        ],
        "elite": 0
      }
    },
    "specific": [
      0,
      0,
      0,
      0,
      0,
      0,
      0,
      0,
      0,
      0,
      0,
      0,
      0,
      0,
      0,
      0
    ]
  },
  "notes": [
    {
      "time": 0,
      "duration": 833,
      "noteType": "Weapon4",
      "abilityId": 62539
    },
    {
      "time": 200,
      "duration": 365,
      "noteType": "Weapon3",
      "abilityId": 62672
    },
    {
      "time": 1033,
      "duration": 800,
      "noteType": "Weapon2",
      "abilityId": 62621
    },
    {
      "time": 1998,
      "duration": 0,
      "noteType": "Profession1",
      "abilityId": 62540
    },
    {
      "time": 1998,
      "duration": 238,
      "noteType": "Weapon1",
      "abilityId": 62611
    },
    {
      "time": 2236,
      "duration": 680,
      "noteType": "Utility3",
      "abilityId": 62662
    },
    {
      "time": 2436,
      "duration": 678,
      "noteType": "Elite",
      "abilityId": 62655
    },
    {
      "time": 3116,
      "duration": 605,
      "noteType": "Weapon5",
      "abilityId": 44296
    },
    {
      "time": 3794,
      "duration": 436,
      "noteType": "Weapon4",
      "abilityId": 45846
    },
    {
      "time": 4399,
      "duration": 603,
      "noteType": "Weapon3",
      "abilityId": 51647
    },
    {
      "time": 4835,
      "duration": 596,
      "noteType": "Weapon2",
      "abilityId": 10532
    },
    {
      "time": 5833,
      "duration": 0,
      "noteType": "WeaponSwap",
      "abilityId": -2
    },
    {
      "time": 6116,
      "duration": 881,
      "noteType": "Utility1",
      "abilityId": 10544
    },
    {
      "time": 6316,
      "duration": 601,
      "noteType": "Weapon3",
      "abilityId": 62511
    },
    {
      "time": 7197,
      "duration": 875,
      "noteType": "Utility1",
      "abilityId": 10544
    },
    {
      "time": 7798,
      "duration": 481,
      "noteType": "Weapon4",
      "abilityId": 10705
    },
    {
      "time": 8673,
      "duration": 844,
      "noteType": "Weapon2",
      "abilityId": 62513
    },
    {
      "time": 9153,
      "duration": 835,
      "noteType": "Weapon5",
      "abilityId": 10706
    },
    {
      "time": 10360,
      "duration": 0,
      "noteType": "Profession1",
      "abilityId": 62567
    },
    {
      "time": 10633,
      "duration": 485,
      "noteType": "Weapon3",
      "abilityId": 62672
    },
    {
      "time": 10833,
      "duration": 802,
      "noteType": "Weapon2",
      "abilityId": 62621
    },
    {
      "time": 11318,
      "duration": 796,
      "noteType": "Weapon5",
      "abilityId": 62563
    },
    {
      "time": 12120,
      "duration": 838,
      "noteType": "Weapon4",
      "abilityId": 62539
    },
    {
      "time": 13554,
      "duration": 604,
      "noteType": "Weapon1",
      "abilityId": 62611
    },
    {
      "time": 14158,
      "duration": 597,
      "noteType": "Weapon1",
      "abilityId": 62611
    },
    {
      "time": 14755,
      "duration": 602,
      "noteType": "Weapon1",
      "abilityId": 62611
    },
    {
      "time": 15357,
      "duration": 600,
      "noteType": "Weapon1",
      "abilityId": 62611
    },
    {
      "time": 15957,
      "duration": 636,
      "noteType": "Weapon1",
      "abilityId": 62611
    },
    {
      "time": 16593,
      "duration": 923,
      "noteType": "Weapon2",
      "abilityId": 62621
    },
    {
      "time": 16793,
      "duration": 477,
      "noteType": "Weapon3",
      "abilityId": 62672
    },
    {
      "time": 17993,
      "duration": 605,
      "noteType": "Weapon1",
      "abilityId": 62611
    },
    {
      "time": 18598,
      "duration": 596,
      "noteType": "Weapon1",
      "abilityId": 62611
    },
    {
      "time": 19194,
      "duration": 599,
      "noteType": "Weapon1",
      "abilityId": 62611
    },
    {
      "time": 19793,
      "duration": 599,
      "noteType": "Weapon1",
      "abilityId": 62611
    },
    {
      "time": 20392,
      "duration": 641,
      "noteType": "Weapon1",
      "abilityId": 62611
    },
    {
      "time": 21033,
      "duration": 840,
      "noteType": "Weapon4",
      "abilityId": 62539
    },
    {
      "time": 21233,
      "duration": 803,
      "noteType": "Weapon2",
      "abilityId": 62621
    },
    {
      "time": 22676,
      "duration": 0,
      "noteType": "Profession1",
      "abilityId": 62540
    },
    {
      "time": 22676,
      "duration": 164,
      "noteType": "Weapon1",
      "abilityId": 62611
    },
    {
      "time": 22840,
      "duration": 836,
      "noteType": "Weapon2",
      "abilityId": 62513
    },
    {
      "time": 23040,
      "duration": 684,
      "noteType": "Utility3",
      "abilityId": 62662
    },
    {
      "time": 25238,
      "duration": 677,
      "noteType": "Heal",
      "abilityId": 62667
    },
    {
      "time": 25915,
      "duration": 876,
      "noteType": "Utility1",
      "abilityId": 10544
    },
    {
      "time": 26115,
      "duration": 481,
      "noteType": "Weapon4",
      "abilityId": 10705
    },
    {
      "time": 26991,
      "duration": 602,
      "noteType": "Weapon3",
      "abilityId": 62511
    },
    {
      "time": 27472,
      "duration": 842,
      "noteType": "Weapon5",
      "abilityId": 10706
    },
    {
      "time": 28074,
      "duration": 844,
      "noteType": "Weapon2",
      "abilityId": 62513
    },
    {
      "time": 29560,
      "duration": 35,
      "noteType": "Weapon1",
      "abilityId": 62517
    },
    {
      "time": 29595,
      "duration": 0,
      "noteType": "WeaponSwap",
      "abilityId": -2
    },
    {
      "time": 29715,
      "duration": 442,
      "noteType": "Weapon4",
      "abilityId": 45846
    },
    {
      "time": 29915,
      "duration": 601,
      "noteType": "Weapon3",
      "abilityId": 51647
    },
    {
      "time": 30357,
      "duration": 874,
      "noteType": "Weapon2",
      "abilityId": 10532
    },
    {
      "time": 31433,
      "duration": 0,
      "noteType": "Profession1",
      "abilityId": 62567
    },
    {
      "time": 31632,
      "duration": 399,
      "noteType": "Weapon3",
      "abilityId": 62672
    },
    {
      "time": 31832,
      "duration": 887,
      "noteType": "Weapon2",
      "abilityId": 62621
    },
    {
      "time": 32231,
      "duration": 797,
      "noteType": "Weapon5",
      "abilityId": 62563
    },
    {
      "time": 33118,
      "duration": 842,
      "noteType": "Weapon4",
      "abilityId": 62539
    },
    {
      "time": 34557,
      "duration": 603,
      "noteType": "Weapon1",
      "abilityId": 62611
    },
    {
      "time": 35160,
      "duration": 592,
      "noteType": "Weapon1",
      "abilityId": 62611
    },
    {
      "time": 35752,
      "duration": 601,
      "noteType": "Weapon1",
      "abilityId": 62611
    },
    {
      "time": 36353,
      "duration": 602,
      "noteType": "Weapon1",
      "abilityId": 62611
    },
    {
      "time": 36955,
      "duration": 639,
      "noteType": "Weapon1",
      "abilityId": 62611
    },
    {
      "time": 37594,
      "duration": 922,
      "noteType": "Weapon2",
      "abilityId": 62621
    },
    {
      "time": 37794,
      "duration": 439,
      "noteType": "Weapon3",
      "abilityId": 62672
    },
    {
      "time": 38955,
      "duration": 604,
      "noteType": "Weapon1",
      "abilityId": 62611
    },
    {
      "time": 39559,
      "duration": 600,
      "noteType": "Weapon1",
      "abilityId": 62611
    },
    {
      "time": 40159,
      "duration": 591,
      "noteType": "Weapon1",
      "abilityId": 62611
    },
    {
      "time": 40750,
      "duration": 607,
      "noteType": "Weapon1",
      "abilityId": 62611
    },
    {
      "time": 41357,
      "duration": 600,
      "noteType": "Weapon1",
      "abilityId": 62611
    },
    {
      "time": 41957,
      "duration": 39,
      "noteType": "Weapon1",
      "abilityId": 62611
    },
    {
      "time": 41996,
      "duration": 838,
      "noteType": "Weapon4",
      "abilityId": 62539
    },
    {
      "time": 42196,
      "duration": 962,
      "noteType": "Weapon2",
      "abilityId": 62621
    },
    {
      "time": 43754,
      "duration": 0,
      "noteType": "Profession1",
      "abilityId": 62540
    },
    {
      "time": 43796,
      "duration": 436,
      "noteType": "Weapon1",
      "abilityId": 10698
    },
    {
      "time": 44232,
      "duration": 165,
      "noteType": "Weapon1",
      "abilityId": 10699
    },
    {
      "time": 44397,
      "duration": 601,
      "noteType": "Weapon5",
      "abilityId": 44296
    },
    {
      "time": 44597,
      "duration": 433,
      "noteType": "Weapon4",
      "abilityId": 45846
    },
    {
      "time": 45198,
      "duration": 605,
      "noteType": "Weapon3",
      "abilityId": 51647
    },
    {
      "time": 45631,
      "duration": 604,
      "noteType": "Weapon2",
      "abilityId": 10532
    },
    {
      "time": 46640,
      "duration": 0,
      "noteType": "WeaponSwap",
      "abilityId": -2
    },
    {
      "time": 46911,
      "duration": 848,
      "noteType": "Weapon2",
      "abilityId": 62513
    },
    {
      "time": 47111,
      "duration": 673,
      "noteType": "Utility3",
      "abilityId": 62662
    },
    {
      "time": 48432,
      "duration": 681,
      "noteType": "Heal",
      "abilityId": 62667
    },
    {
      "time": 49113,
      "duration": 877,
      "noteType": "Utility1",
      "abilityId": 10544
    },
    {
      "time": 49313,
      "duration": 483,
      "noteType": "Weapon4",
      "abilityId": 10705
    },
    {
      "time": 50190,
      "duration": 607,
      "noteType": "Weapon3",
      "abilityId": 62511
    },
    {
      "time": 50673,
      "duration": 834,
      "noteType": "Weapon5",
      "abilityId": 10706
    },
    {
      "time": 51280,
      "duration": 682,
      "noteType": "Elite",
      "abilityId": 62655
    },
    {
      "time": 52313,
      "duration": 0,
      "noteType": "Profession1",
      "abilityId": 62567
    },
    {
      "time": 52596,
      "duration": 402,
      "noteType": "Weapon3",
      "abilityId": 62672
    },
    {
      "time": 52796,
      "duration": 799,
      "noteType": "Weapon2",
      "abilityId": 62621
    },
    {
      "time": 53198,
      "duration": 798,
      "noteType": "Weapon5",
      "abilityId": 62563
    },
    {
      "time": 53997,
      "duration": 843,
      "noteType": "Weapon4",
      "abilityId": 62539
    },
    {
      "time": 55438,
      "duration": 597,
      "noteType": "Weapon1",
      "abilityId": 62611
    },
    {
      "time": 56035,
      "duration": 602,
      "noteType": "Weapon1",
      "abilityId": 62611
    },
    {
      "time": 56637,
      "duration": 613,
      "noteType": "Weapon1",
      "abilityId": 62611
    },
    {
      "time": 57250,
      "duration": 581,
      "noteType": "Weapon1",
      "abilityId": 62611
    },
    {
      "time": 57831,
      "duration": 640,
      "noteType": "Weapon1",
      "abilityId": 62611
    },
    {
      "time": 58471,
      "duration": 922,
      "noteType": "Weapon2",
      "abilityId": 62621
    },
    {
      "time": 58671,
      "duration": 480,
      "noteType": "Weapon3",
      "abilityId": 62672
    },
    {
      "time": 59873,
      "duration": 600,
      "noteType": "Weapon1",
      "abilityId": 62611
    },
    {
      "time": 60473,
      "duration": 603,
      "noteType": "Weapon1",
      "abilityId": 62611
    },
    {
      "time": 61076,
      "duration": 594,
      "noteType": "Weapon1",
      "abilityId": 62611
    },
    {
      "time": 61670,
      "duration": 606,
      "noteType": "Weapon1",
      "abilityId": 62611
    },
    {
      "time": 62276,
      "duration": 633,
      "noteType": "Weapon1",
      "abilityId": 62611
    },
    {
      "time": 62909,
      "duration": 842,
      "noteType": "Weapon4",
      "abilityId": 62539
    },
    {
      "time": 63109,
      "duration": 800,
      "noteType": "Weapon2",
      "abilityId": 62621
    },
    {
      "time": 64551,
      "duration": 0,
      "noteType": "Profession1",
      "abilityId": 62540
    },
    {
      "time": 64551,
      "duration": 158,
      "noteType": "Weapon1",
      "abilityId": 62611
    },
    {
      "time": 64709,
      "duration": 842,
      "noteType": "Weapon2",
      "abilityId": 62513
    },
    {
      "time": 64909,
      "duration": 883,
      "noteType": "Utility1",
      "abilityId": 10544
    },
    {
      "time": 65750,
      "duration": 474,
      "noteType": "Weapon4",
      "abilityId": 10705
    },
    {
      "time": 66635,
      "duration": 598,
      "noteType": "Weapon3",
      "abilityId": 62511
    },
    {
      "time": 67992,
      "duration": 839,
      "noteType": "Weapon5",
      "abilityId": 10706
    },
    {
      "time": 68590,
      "duration": 682,
      "noteType": "Utility3",
      "abilityId": 62662
    },
    {
      "time": 69911,
      "duration": 681,
      "noteType": "Heal",
      "abilityId": 62667
    },
    {
      "time": 70592,
      "duration": 843,
      "noteType": "Weapon2",
      "abilityId": 62513
    },
    {
      "time": 71435,
      "duration": 75,
      "noteType": "Weapon1",
      "abilityId": 62517
    },
    {
      "time": 71510,
      "duration": 0,
      "noteType": "WeaponSwap",
      "abilityId": -2
    },
    {
      "time": 71714,
      "duration": 435,
      "noteType": "Weapon4",
      "abilityId": 45846
    },
    {
      "time": 71914,
      "duration": 600,
      "noteType": "Weapon3",
      "abilityId": 51647
    },
    {
      "time": 72349,
      "duration": 884,
      "noteType": "Weapon2",
      "abilityId": 10532
    },
    {
      "time": 73432,
      "duration": 0,
      "noteType": "Profession1",
      "abilityId": 62567
    },
    {
      "time": 73633,
      "duration": 438,
      "noteType": "Weapon3",
      "abilityId": 62672
    },
    {
      "time": 73833,
      "duration": 805,
      "noteType": "Weapon2",
      "abilityId": 62621
    },
    {
      "time": 74271,
      "duration": 798,
      "noteType": "Weapon5",
      "abilityId": 62563
    },
    {
      "time": 75076,
      "duration": 842,
      "noteType": "Weapon4",
      "abilityId": 62539
    },
    {
      "time": 76516,
      "duration": 595,
      "noteType": "Weapon1",
      "abilityId": 62611
    },
    {
      "time": 77111,
      "duration": 601,
      "noteType": "Weapon1",
      "abilityId": 62611
    },
    {
      "time": 77712,
      "duration": 603,
      "noteType": "Weapon1",
      "abilityId": 62611
    },
    {
      "time": 78315,
      "duration": 599,
      "noteType": "Weapon1",
      "abilityId": 62611
    },
    {
      "time": 78914,
      "duration": 641,
      "noteType": "Weapon1",
      "abilityId": 62611
    },
    {
      "time": 79555,
      "duration": 913,
      "noteType": "Weapon2",
      "abilityId": 62621
    },
    {
      "time": 79755,
      "duration": 404,
      "noteType": "Weapon3",
      "abilityId": 62672
    },
    {
      "time": 80872,
      "duration": 605,
      "noteType": "Weapon1",
      "abilityId": 62611
    },
    {
      "time": 81477,
      "duration": 596,
      "noteType": "Weapon1",
      "abilityId": 62611
    },
    {
      "time": 82073,
      "duration": 601,
      "noteType": "Weapon1",
      "abilityId": 62611
    },
    {
      "time": 82674,
      "duration": 602,
      "noteType": "Weapon1",
      "abilityId": 62611
    },
    {
      "time": 83276,
      "duration": 594,
      "noteType": "Weapon1",
      "abilityId": 62611
    },
    {
      "time": 83870,
      "duration": 43,
      "noteType": "Weapon1",
      "abilityId": 62611
    },
    {
      "time": 83913,
      "duration": 836,
      "noteType": "Weapon4",
      "abilityId": 62539
    },
    {
      "time": 84113,
      "duration": 923,
      "noteType": "Weapon2",
      "abilityId": 62621
    },
    {
      "time": 85635,
      "duration": 0,
      "noteType": "Profession1",
      "abilityId": 62540
    },
    {
      "time": 85672,
      "duration": 121,
      "noteType": "Weapon1",
      "abilityId": 10698
    },
    {
      "time": 85793,
      "duration": 600,
      "noteType": "Weapon5",
      "abilityId": 44296
    },
    {
      "time": 85993,
      "duration": 438,
      "noteType": "Weapon4",
      "abilityId": 45846
    },
    {
      "time": 86593,
      "duration": 597,
      "noteType": "Weapon3",
      "abilityId": 51647
    },
    {
      "time": 87031,
      "duration": 605,
      "noteType": "Weapon2",
      "abilityId": 10532
    },
    {
      "time": 88032,
      "duration": 0,
      "noteType": "WeaponSwap",
      "abilityId": -2
    },
    {
      "time": 88310,
      "duration": 846,
      "noteType": "Weapon2",
      "abilityId": 62513
    },
    {
      "time": 88510,
      "duration": 874,
      "noteType": "Utility1",
      "abilityId": 10544
    },
    {
      "time": 89356,
      "duration": 601,
      "noteType": "Weapon3",
      "abilityId": 62511
    },
    {
      "time": 90230,
      "duration": 884,
      "noteType": "Utility1",
      "abilityId": 10544
    },
    {
      "time": 90831,
      "duration": 476,
      "noteType": "Weapon4",
      "abilityId": 10705
    },
    {
      "time": 91715,
      "duration": 681,
      "noteType": "Utility3",
      "abilityId": 62662
    },
    {
      "time": 92672,
      "duration": 680,
      "noteType": "Heal",
      "abilityId": 62667
    },
    {
      "time": 93352,
      "duration": 839,
      "noteType": "Weapon5",
      "abilityId": 10706
    },
    {
      "time": 93954,
      "duration": 0,
      "noteType": "Profession1",
      "abilityId": 62567
    },
    {
      "time": 94191,
      "duration": 402,
      "noteType": "Weapon3",
      "abilityId": 62672
    },
    {
      "time": 94391,
      "duration": 919,
      "noteType": "Weapon2",
      "abilityId": 62621
    },
    {
      "time": 94793,
      "duration": 841,
      "noteType": "Weapon4",
      "abilityId": 62539
    },
    {
      "time": 96353,
      "duration": 601,
      "noteType": "Weapon1",
      "abilityId": 62611
    },
    {
      "time": 96954,
      "duration": 596,
      "noteType": "Weapon1",
      "abilityId": 62611
    },
    {
      "time": 97550,
      "duration": 599,
      "noteType": "Weapon1",
      "abilityId": 62611
    },
    {
      "time": 98149,
      "duration": 600,
      "noteType": "Weapon1",
      "abilityId": 62611
    },
    {
      "time": 98749,
      "duration": 607,
      "noteType": "Weapon1",
      "abilityId": 62611
    },
    {
      "time": 99356,
      "duration": 638,
      "noteType": "Weapon1",
      "abilityId": 62611
    },
    {
      "time": 99994,
      "duration": 921,
      "noteType": "Weapon2",
      "abilityId": 62621
    },
    {
      "time": 100194,
      "duration": 396,
      "noteType": "Weapon3",
      "abilityId": 62672
    },
    {
      "time": 101311,
      "duration": 603,
      "noteType": "Weapon1",
      "abilityId": 62611
    },
    {
      "time": 101914,
      "duration": 600,
      "noteType": "Weapon1",
      "abilityId": 62611
    },
    {
      "time": 102514,
      "duration": 603,
      "noteType": "Weapon1",
      "abilityId": 62611
    },
    {
      "time": 103117,
      "duration": 592,
      "noteType": "Weapon1",
      "abilityId": 62611
    },
    {
      "time": 103709,
      "duration": 599,
      "noteType": "Weapon1",
      "abilityId": 62611
    },
    {
      "time": 104308,
      "duration": 40,
      "noteType": "Weapon1",
      "abilityId": 62611
    },
    {
      "time": 104348,
      "duration": 846,
      "noteType": "Weapon4",
      "abilityId": 62539
    },
    {
      "time": 104548,
      "duration": 960,
      "noteType": "Weapon2",
      "abilityId": 62621
    },
    {
      "time": 106115,
      "duration": 0,
      "noteType": "Profession1",
      "abilityId": 62540
    },
    {
      "time": 106154,
      "duration": 158,
      "noteType": "Weapon1",
      "abilityId": 62517
    },
    {
      "time": 106312,
      "duration": 677,
      "noteType": "Elite",
      "abilityId": 62655
    },
    {
      "time": 106512,
      "duration": 842,
      "noteType": "Weapon2",
      "abilityId": 62513
    },
    {
      "time": 107189,
      "duration": 881,
      "noteType": "Utility1",
      "abilityId": 10544
    },
    {
      "time": 108910,
      "duration": 483,
      "noteType": "Weapon4",
      "abilityId": 10705
    },
    {
      "time": 109791,
      "duration": 595,
      "noteType": "Weapon3",
      "abilityId": 62511
    },
    {
      "time": 110274,
      "duration": 563,
      "noteType": "Weapon5",
      "abilityId": 10706
    },
    {
      "time": 111231,
      "duration": 0,
      "noteType": "WeaponSwap",
      "abilityId": -2
    },
    {
      "time": 111508,
      "duration": 440,
      "noteType": "Weapon4",
      "abilityId": 45846
    },
    {
      "time": 111708,
      "duration": 601,
      "noteType": "Weapon3",
      "abilityId": 51647
    },
    {
      "time": 112148,
      "duration": 882,
      "noteType": "Weapon2",
      "abilityId": 10532
    },
    {
      "time": 112749,
      "duration": 647,
      "noteType": "Weapon5",
      "abilityId": 44296
    }
  ]
}